{
  "__inputs": [],
  "__requires": [],
  "annotations": { "list": [] },
  "editable": true,
  "fiscalYearStartMonth": 0,
  "graphTooltip": 1,
  "id": null,
  "links": [],
  "panels": [
    {
      "collapsed": false,
      "gridPos": { "h": 1, "w": 24, "x": 0, "y": 0 },
      "id": 100,
      "title": "Overview",
      "type": "row"
    },
    {
      "datasource": { "type": "prometheus", "uid": "prometheus" },
      "fieldConfig": {
        "defaults": {
          "color": { "mode": "thresholds" },
          "thresholds": { "mode": "absolute", "steps": [
            { "color": "blue", "value": null }
          ]},
          "unit": "short",
          "mappings": []
        }
      },
      "gridPos": { "h": 4, "w": 4, "x": 0, "y": 1 },
      "id": 1,
      "options": { "reduceOptions": { "calcs": ["lastNotNull"] }, "orientation": "auto", "textMode": "auto", "colorMode": "background", "graphMode": "none" },
      "title": "Total Scans",
      "type": "stat",
      "targets": [{ "datasource": { "type": "prometheus", "uid": "prometheus" }, "expr": "sum(saptara_scans_total)", "legendFormat": "Scans", "refId": "A" }]
    },
    {
      "datasource": { "type": "prometheus", "uid": "prometheus" },
      "fieldConfig": {
        "defaults": {
          "color": { "mode": "thresholds" },
          "thresholds": { "mode": "absolute", "steps": [
            { "color": "green", "value": null },
            { "color": "yellow", "value": 10 },
            { "color": "red", "value": 50 }
          ]},
          "unit": "short"
        }
      },
      "gridPos": { "h": 4, "w": 4, "x": 4, "y": 1 },
      "id": 2,
      "options": { "reduceOptions": { "calcs": ["lastNotNull"] }, "colorMode": "background", "graphMode": "none" },
      "title": "Vulnerabilities Found",
      "type": "stat",
      "targets": [{ "datasource": { "type": "prometheus", "uid": "prometheus" }, "expr": "sum(saptara_vulnerabilities_found_total)", "legendFormat": "Vulns", "refId": "A" }]
    },
    {
      "datasource": { "type": "prometheus", "uid": "prometheus" },
      "fieldConfig": {
        "defaults": {
          "color": { "mode": "thresholds" },
          "thresholds": { "mode": "absolute", "steps": [
            { "color": "green", "value": null }
          ]},
          "unit": "short"
        }
      },
      "gridPos": { "h": 4, "w": 4, "x": 8, "y": 1 },
      "id": 3,
      "options": { "reduceOptions": { "calcs": ["lastNotNull"] }, "colorMode": "background", "graphMode": "none" },
      "title": "Total Tests Executed",
      "type": "stat",
      "targets": [{ "datasource": { "type": "prometheus", "uid": "prometheus" }, "expr": "sum(saptara_tests_total)", "legendFormat": "Tests", "refId": "A" }]
    },
    {
      "datasource": { "type": "prometheus", "uid": "prometheus" },
      "fieldConfig": {
        "defaults": {
          "color": { "mode": "thresholds" },
          "thresholds": { "mode": "absolute", "steps": [
            { "color": "green", "value": null },
            { "color": "orange", "value": 1 }
          ]},
          "unit": "short"
        }
      },
      "gridPos": { "h": 4, "w": 4, "x": 12, "y": 1 },
      "id": 4,
      "options": { "reduceOptions": { "calcs": ["lastNotNull"] }, "colorMode": "background", "graphMode": "none" },
      "title": "Active Scans",
      "type": "stat",
      "targets": [{ "datasource": { "type": "prometheus", "uid": "prometheus" }, "expr": "sum(saptara_active_scans)", "legendFormat": "Active", "refId": "A" }]
    },
    {
      "datasource": { "type": "prometheus", "uid": "prometheus" },
      "fieldConfig": {
        "defaults": {
          "color": { "mode": "thresholds" },
          "thresholds": { "mode": "absolute", "steps": [
            { "color": "red", "value": null },
            { "color": "green", "value": 1 }
          ]},
          "unit": "short",
          "mappings": [
            { "options": { "0": { "text": "DOWN" }, "1": { "text": "UP" } }, "type": "value" }
          ]
        }
      },
      "gridPos": { "h": 4, "w": 8, "x": 16, "y": 1 },
      "id": 5,
      "options": { "reduceOptions": { "calcs": ["lastNotNull"] }, "colorMode": "background", "graphMode": "none", "orientation": "horizontal" },
      "title": "Services Up",
      "type": "stat",
      "targets": [
        { "datasource": { "type": "prometheus", "uid": "prometheus" }, "expr": "up{job=\"orchestrator\"}", "legendFormat": "Orchestrator", "refId": "A" },
        { "datasource": { "type": "prometheus", "uid": "prometheus" }, "expr": "up{job=\"scanner\"}", "legendFormat": "Scanner", "refId": "B" },
        { "datasource": { "type": "prometheus", "uid": "prometheus" }, "expr": "up{job=\"simulator\"}", "legendFormat": "Simulator", "refId": "C" },
        { "datasource": { "type": "prometheus", "uid": "prometheus" }, "expr": "up{job=\"validator\"}", "legendFormat": "Validator", "refId": "D" }
      ]
    },
    {
      "collapsed": false,
      "gridPos": { "h": 1, "w": 24, "x": 0, "y": 5 },
      "id": 101,
      "title": "Scan Activity",
      "type": "row"
    },
    {
      "datasource": { "type": "prometheus", "uid": "prometheus" },
      "fieldConfig": {
        "defaults": { "color": { "mode": "palette-classic" }, "unit": "short" },
        "overrides": []
      },
      "gridPos": { "h": 8, "w": 12, "x": 0, "y": 6 },
      "id": 6,
      "options": { "tooltip": { "mode": "multi" }, "legend": { "displayMode": "list", "placement": "bottom" } },
      "title": "Scans Started Over Time (by service)",
      "type": "timeseries",
      "targets": [
        { "datasource": { "type": "prometheus", "uid": "prometheus" }, "expr": "increase(saptara_scans_total{service=\"scanner\"}[5m])", "legendFormat": "Scanner", "refId": "A" },
        { "datasource": { "type": "prometheus", "uid": "prometheus" }, "expr": "increase(saptara_scans_total{service=\"simulator\"}[5m])", "legendFormat": "Simulator", "refId": "B" },
        { "datasource": { "type": "prometheus", "uid": "prometheus" }, "expr": "increase(saptara_scans_total{service=\"validator\"}[5m])", "legendFormat": "Validator", "refId": "C" }
      ]
    },
    {
      "datasource": { "type": "prometheus", "uid": "prometheus" },
      "fieldConfig": {
        "defaults": { "color": { "mode": "palette-classic" }, "unit": "short" },
        "overrides": []
      },
      "gridPos": { "h": 8, "w": 12, "x": 12, "y": 6 },
      "id": 7,
      "options": { "tooltip": { "mode": "multi" }, "legend": { "displayMode": "list", "placement": "bottom" } },
      "title": "Tests Executed Over Time (by status)",
      "type": "timeseries",
      "targets": [
        { "datasource": { "type": "prometheus", "uid": "prometheus" }, "expr": "increase(saptara_tests_total{status=\"passed\"}[5m])", "legendFormat": "Passed", "refId": "A" },
        { "datasource": { "type": "prometheus", "uid": "prometheus" }, "expr": "increase(saptara_tests_total{status=\"failed\"}[5m])", "legendFormat": "Failed", "refId": "B" },
        { "datasource": { "type": "prometheus", "uid": "prometheus" }, "expr": "increase(saptara_tests_total{status=\"vulnerable\"}[5m])", "legendFormat": "Vulnerable", "refId": "C" },
        { "datasource": { "type": "prometheus", "uid": "prometheus" }, "expr": "increase(saptara_tests_total{status=\"blocked\"}[5m])", "legendFormat": "Blocked", "refId": "D" }
      ]
    },
    {
      "collapsed": false,
      "gridPos": { "h": 1, "w": 24, "x": 0, "y": 14 },
      "id": 102,
      "title": "Vulnerabilities",
      "type": "row"
    },
    {
      "datasource": { "type": "prometheus", "uid": "prometheus" },
      "fieldConfig": {
        "defaults": { "color": { "mode": "palette-classic" }, "unit": "short" },
        "overrides": []
      },
      "gridPos": { "h": 8, "w": 12, "x": 0, "y": 15 },
      "id": 8,
      "options": { "tooltip": { "mode": "multi" }, "legend": { "displayMode": "list", "placement": "bottom" } },
      "title": "Vulnerabilities Found by Severity",
      "type": "timeseries",
      "targets": [
        { "datasource": { "type": "prometheus", "uid": "prometheus" }, "expr": "sum by(severity) (increase(saptara_vulnerabilities_found_total[5m]))", "legendFormat": "{{severity}}", "refId": "A" }
      ]
    },
    {
      "datasource": { "type": "prometheus", "uid": "prometheus" },
      "fieldConfig": {
        "defaults": { "color": { "mode": "palette-classic" }, "unit": "short" },
        "overrides": []
      },
      "gridPos": { "h": 8, "w": 12, "x": 12, "y": 15 },
      "id": 9,
      "options": { "tooltip": { "mode": "multi" }, "legend": { "displayMode": "list", "placement": "bottom" } },
      "title": "Tests by Category (Scanner)",
      "type": "timeseries",
      "targets": [
        { "datasource": { "type": "prometheus", "uid": "prometheus" }, "expr": "sum by(category) (increase(saptara_tests_total{service=\"scanner\"}[5m]))", "legendFormat": "{{category}}", "refId": "A" }
      ]
    },
    {
      "collapsed": false,
      "gridPos": { "h": 1, "w": 24, "x": 0, "y": 23 },
      "id": 103,
      "title": "Performance",
      "type": "row"
    },
    {
      "datasource": { "type": "prometheus", "uid": "prometheus" },
      "fieldConfig": {
        "defaults": { "color": { "mode": "palette-classic" }, "unit": "s" },
        "overrides": []
      },
      "gridPos": { "h": 8, "w": 12, "x": 0, "y": 24 },
      "id": 10,
      "options": { "tooltip": { "mode": "multi" }, "legend": { "displayMode": "list", "placement": "bottom" } },
      "title": "Average Scan Duration by Service",
      "type": "timeseries",
      "targets": [
        { "datasource": { "type": "prometheus", "uid": "prometheus" }, "expr": "rate(saptara_scan_duration_seconds_sum[5m]) / rate(saptara_scan_duration_seconds_count[5m])", "legendFormat": "{{service}}", "refId": "A" }
      ]
    },
    {
      "datasource": { "type": "prometheus", "uid": "prometheus" },
      "fieldConfig": {
        "defaults": { "color": { "mode": "palette-classic" }, "unit": "s" },
        "overrides": []
      },
      "gridPos": { "h": 8, "w": 12, "x": 12, "y": 24 },
      "id": 11,
      "options": { "tooltip": { "mode": "multi" }, "legend": { "displayMode": "list", "placement": "bottom" } },
      "title": "Outbound HTTP Request Latency",
      "type": "timeseries",
      "targets": [
        { "datasource": { "type": "prometheus", "uid": "prometheus" }, "expr": "rate(saptara_http_request_duration_seconds_sum[5m]) / rate(saptara_http_request_duration_seconds_count[5m])", "legendFormat": "{{service}} {{method}}", "refId": "A" }
      ]
    }
  ],
  "refresh": "30s",
  "schemaVersion": 38,
  "tags": ["saptara", "security"],
  "templating": { "list": [] },
  "time": { "from": "now-6h", "to": "now" },
  "timepicker": {},
  "timezone": "Asia/Kolkata",
  "title": "SAPTARA — Security Assessment Overview",
  "uid": "saptara-overview",
  "version": 1
}
